README.md
setup.cfg
setup.py
bin/soundforest
bin/soundforest-mkv
soundforest/__init__.py
soundforest/cli.py
soundforest/database.py
soundforest/defaults.py
soundforest/formats.py
soundforest/log.py
soundforest/metadata.py
soundforest/models.py
soundforest/playlist.py
soundforest/prefixes.py
soundforest/sync.py
soundforest/tree.py
soundforest.egg-info/PKG-INFO
soundforest.egg-info/SOURCES.txt
soundforest.egg-info/dependency_links.txt
soundforest.egg-info/requires.txt
soundforest.egg-info/top_level.txt
soundforest/converters/__init__.py
soundforest/converters/matroska.py
soundforest/tags/__init__.py
soundforest/tags/albumart.py
soundforest/tags/constants.py
soundforest/tags/tagparser.py
soundforest/tags/xmltag.py
soundforest/tags/formats/__init__.py
soundforest/tags/formats/aac.py
soundforest/tags/formats/flac.py
soundforest/tags/formats/mp3.py
soundforest/tags/formats/vorbis.py