Metadata-Version: 1.0
Name: soundforest
Version: 4.3.0
Summary: Audio file library manager
Home-page: https://github.com/hile/soundforest
Author: Ilkka Tuohela
Author-email: hile@iki.fi
License: PSF
Keywords: Sound Audio File Tree Codec Database
Platform: UNKNOWN
